dicomdeidentifier/__init__.py
dicomdeidentifier/deidentify_dicom.py
dicomdeidentifier/rule_sets.py
dicomdeidentifier-0.2.4.dist-info/WHEEL
dicomdeidentifier-0.2.4.dist-info/METADATA
dicomdeidentifier-0.2.4.dist-info/RECORD
