Metadata-Version: 2.1
Name: dicomdeidentifier
Version: 0.2.4
Summary: Deidentifies Dicom tags
License: MIT
Author: barbara73
Author-email: barbara.jesacher@gmail.com
Requires-Python: >=3.9,<4.0
Classifier: License :: OSI Approved :: MIT License
Classifier: Programming Language :: Python :: 3
Classifier: Programming Language :: Python :: 3.9
Classifier: Programming Language :: Python :: 3.10
Classifier: Programming Language :: Python :: 3.11
Requires-Dist: Jinja2 (>=3.1.2,<4.0.0)
Requires-Dist: idiscore (>=1.0.1,<2.0.0)
Requires-Dist: pytest (>=7.1.2,<8.0.0)
